llm_chain/__init__.py
llm_chain/conversation_chain.py
llm_chain/llm.py
llm_chain/templates.py
llm_chain/ui/__init__.py
llm_chain/ui/main.py
llm_inference/__init__.py
llm_inference/download.py
llm_inference/model.py
llm_inference/serve.py
llm_inference/token_manipulation.py
llm_inference-0.0.6.dist-info/LICENSE
llm_inference-0.0.6.dist-info/METADATA
llm_inference-0.0.6.dist-info/WHEEL
llm_inference-0.0.6.dist-info/top_level.txt
llm_inference-0.0.6.dist-info/RECORD
