Metadata-Version: 2.1
Name: llm-inference
Version: 0.0.6
Summary: Large Language Models Inference API and Applications
Home-page: https://github.com/aniketmaurya/llm-inference
Author: Aniket Maurya
Author-email: theaniketmaurya@gmail.com
License: Apache License 2.0
Keywords: LLM,LLaMA,GPT,Falcon
Requires-Python: >=3.8
License-File: LICENSE
Requires-Dist: python-dotenv
Requires-Dist: huggingface-hub
Requires-Dist: langchain (>=0.0.94)
Requires-Dist: openai (>=0.26.5)
Requires-Dist: streamlit (>=1.19.0)
Requires-Dist: streamlit-chat (>=0.0.2.1)
Requires-Dist: transformers (>=4.26.1)
Requires-Dist: fastapi (>=0.88.0)
Requires-Dist: gradio
Provides-Extra: dev
Requires-Dist: pytest ; extra == 'dev'
Requires-Dist: pre-commit ; extra == 'dev'
Requires-Dist: black ; extra == 'dev'
Requires-Dist: isort ; extra == 'dev'
Requires-Dist: build ; extra == 'dev'
Requires-Dist: twine ; extra == 'dev'
